{
  "id": "boomdandy",
  "name": "Boomdandy",
  "edition": "carousel",
  "team": "minion",
  "firstNightReminder": "",
  "otherNightReminder": "",
  "reminders": [],
  "remindersGlobal": [],
  "setup": false,
  "ability": "If you are executed, all but 3 players die. After a 10 to 1 countdown, the player with the most players pointing at them, dies.",
  "flavor": "\"Tick... Tick... Tick... TOCK.\"",
  "image": "icons/carousel/boomdandy.webp",
  "firstNight": 0,
  "otherNight": 0,
  "jinxes": [
    {
      "id": "plaguedoctor",
      "reason": "If the Storyteller would gain the Boomdandy ability, a player becomes the Boomdandy."
    }
  ],
  "_remindersFetched": true
}