{
  "id": "saint",
  "name": "Saint",
  "edition": "tb",
  "team": "outsider",
  "firstNightReminder": "",
  "otherNightReminder": "",
  "reminders": [],
  "remindersGlobal": [],
  "setup": false,
  "ability": "If you die by execution, your team loses.",
  "flavor": "\"Wisdom begets peace. Patience begets wisdom. Fear not, for the time shall come when fear too shall pass. Let us pray, and may the unity of our vision make saints of us all.\"",
  "image": "icons/tb/saint.webp",
  "firstNight": 0,
  "otherNight": 0,
  "_remindersFetched": true
}
